Metadata-Version: 2.1
Name: DataQuality-package
Version: 0.1
Summary: Package to perform Data Quality Check 
Home-page: https://github.com/Pannu2095/DataQuality
Author: Parveen Kaur
Author-email: parveen.kaur@gds.ey.com
License: MIT
Platform: UNKNOWN
